pbar_io/__init__.py
pbar_io/client.py
pbar_io/integrations.py
pbar_io/tqdm.py
pbar_io-0.1.0.dist-info/licenses/LICENSE
pbar_io-0.1.0.dist-info/METADATA
pbar_io-0.1.0.dist-info/WHEEL
pbar_io-0.1.0.dist-info/top_level.txt
pbar_io-0.1.0.dist-info/RECORD
