Metadata-Version: 2.4
Name: pbar-io
Version: 0.1.0
Summary: Share progress bars via pbar.io - works with tqdm, rich, and more
Author-email: "pbar.io" <hello@pbar.io>
License-Expression: MIT
Project-URL: Homepage, https://pbar.io
Project-URL: Repository, https://github.com/rhodes73/pbar.io
Project-URL: Documentation, https://pbar.io/docs
Project-URL: Bug Tracker, https://github.com/rhodes73/pbar.io/issues
Classifier: Development Status :: 4 - Beta
Classifier: Intended Audience :: Developers
Classifier: Topic :: Software Development :: Libraries :: Python Modules
Classifier: Programming Language :: Python :: 3
Classifier: Programming Language :: Python :: 3.7
Classifier: Programming Language :: Python :: 3.8
Classifier: Programming Language :: Python :: 3.9
Classifier: Programming Language :: Python :: 3.10
Classifier: Programming Language :: Python :: 3.11
Classifier: Programming Language :: Python :: 3.12
Requires-Python: >=3.7
License-File: LICENSE
Requires-Dist: requests>=2.25.0
Requires-Dist: tqdm>=4.60.0
Provides-Extra: dev
Requires-Dist: pytest>=6.0; extra == "dev"
Requires-Dist: black>=22.0; extra == "dev"
Requires-Dist: flake8>=3.9; extra == "dev"
Dynamic: license-file
